ProdOPS/__init__.py
ProdOPS/admin.py
ProdOPS/app_settings.py
ProdOPS/apps.py
ProdOPS/auth_hooks.py
ProdOPS/models.py
ProdOPS/tasks.py
ProdOPS/urls.py
ProdOPS/views.py
ProdOPS/locale/.gitkeep
ProdOPS/migrations/0001_initial.py
ProdOPS/migrations/__init__.py
ProdOPS/static/ProdOPS/.gitkeep
ProdOPS/templates/ProdOPS/base.html
ProdOPS/templates/ProdOPS/index.html
ProdOPS/tests/__init__.py
ProdOPS/tests/test_example.py
prodops-0.0.9.dist-info/METADATA
prodops-0.0.9.dist-info/WHEEL
prodops-0.0.9.dist-info/licenses/LICENSE
prodops-0.0.9.dist-info/RECORD
